conversion/__init__.py
conversion/conversion.py
s2w-1.0.0.dist-info/LICENSE
s2w-1.0.0.dist-info/METADATA
s2w-1.0.0.dist-info/WHEEL
s2w-1.0.0.dist-info/top_level.txt
s2w-1.0.0.dist-info/RECORD
