Metadata-Version: 2.1
Name: s2w
Version: 1.0.0
Summary: A package that can convert a paragraph of spoken english to written english
Home-page: https://github.com/Eshan-Agarwal/Abbreviations-Conversion
Author: Eshan Agarwal
Author-email: eshanagarwal12@gmail.com
License: UNKNOWN
Platform: UNKNOWN
Classifier: Programming Language :: Python :: 3
Classifier: Programming Language :: Python :: 3.4
Classifier: Programming Language :: Python :: 3.5
Classifier: Programming Language :: Python :: 3.6
Classifier: License :: OSI Approved :: GNU General Public License v3 (GPLv3)
Requires-Dist: ipython (>=6)
Requires-Dist: nbformat (>=4)
Requires-Dist: nbconvert (>=5)
Requires-Dist: requests (>=2)
Requires-Dist: SpeechRecognition (>=3)
